puppetdb/__init__.py
puppetdb_tools-2.2.5.dist-info/LICENSE
puppetdb_tools-2.2.5.dist-info/METADATA
puppetdb_tools-2.2.5.dist-info/WHEEL
puppetdb_tools-2.2.5.dist-info/top_level.txt
puppetdb_tools-2.2.5.dist-info/RECORD
