Metadata-Version: 2.1
Name: puppetdb-tools
Version: 2.2.5
Summary: puppetdb tools and shared libraries
Home-page: http://github.com/tskirvin/puppetdb-tools
Author: Tim Skirvin
Author-email: tskirvin@fnal.gov
Maintainer: Tim Skirvin
Maintainer-email: tskirvin@fnal.gov
License: Perl Artistic
Keywords: puppetdb,puppet
Platform: UNKNOWN
